.DS_Store
DeepMatter/.DS_Store
DeepMatter/__init__.py
DeepMatter/Autoencoders/.DS_Store
DeepMatter/Autoencoders/__init__.py
DeepMatter/Autoencoders/Conv2d/Auto_format.py
DeepMatter/Autoencoders/Conv2d/__init__.py
DeepMatter/Autoencoders/Conv2d/beta_vae.py
DeepMatter/Autoencoders/Conv2d/cycle_consistant.py
DeepMatter/Autoencoders/Conv2d/nn.py
DeepMatter/Autoencoders/Conv2d/switching_visuzalizer.py
DeepMatter/Autoencoders/Conv2d/util.py
DeepMatter/VAE_PFM/__init__.py
DeepMatter/VAE_PFM/dictionary_learning.py
DeepMatter/VAE_PFM/file.py
DeepMatter/VAE_PFM/machine_learning.py
DeepMatter/rand_util/__init__.py
DeepMatter/rand_util/rand_gen.py
DeepMatter/spectral_fitters/__init__.py
DeepMatter/spectral_fitters/gaussian.py
DeepMatter/spectral_fitters/nn.py
DeepMatter/spectral_fitters/voigt.py
DeepMatter/util/__init__.py
DeepMatter/util/i_o.py
DeepMatter/util/io.py
DeepMatter/util/io_.py
DeepMatter/util/one_dim_data_generators.py
DeepMatter/util/scalars.py
DeepMatter/util/search_tools.py
DeepMatter/util/torch_util.py
DeepMatter/util/preprocessing/__init__.py
DeepMatter/util/preprocessing/preprocess_1d.py
DeepMatter/viz/__init__.py
DeepMatter/viz/embeddings.py
DeepMatter/viz/format.py
DeepMatter/viz/movies.py
DeepMatter-0.0.59.dist-info/.DS_Store
DeepMatter-0.0.59.dist-info/LICENSE
DeepMatter-0.0.59.dist-info/METADATA
DeepMatter-0.0.59.dist-info/WHEEL
DeepMatter-0.0.59.dist-info/top_level.txt
DeepMatter-0.0.59.dist-info/RECORD
